README.md
setup.py
ledgerpy/__init__.py
ledgerpy/ledger.py
ledgerpy.egg-info/PKG-INFO
ledgerpy.egg-info/SOURCES.txt
ledgerpy.egg-info/dependency_links.txt
ledgerpy.egg-info/not-zip-safe
ledgerpy.egg-info/requires.txt
ledgerpy.egg-info/top_level.txt