Metadata-Version: 1.0
Name: ledgerpy
Version: 0.1.0
Summary: python module for Ledger Nano S
Home-page: https://github.com/zondax/ledger-py
Author: ZondaX GmbH
Author-email: info@zondax.ch
License: Apache 2.0
Platform: UNKNOWN
